[
  [
    {
      "src": "assets/icons/python-svgrepo-com.svg",
      "text": "Python"
    },
    {
      "src": "assets/icons/flask.svg",
      "text": "Flask"
    },
    {
      "src": "assets/icons/flutter-svgrepo-com.svg",
      "text": "Flutter"
    },
    {
      "src": "assets/icons/postgresql-svgrepo-com.svg",
      "text": "PostgreSQL"
    },
    {
      "src": "assets/icons/sqlalchemy.svg",
      "text": "SQLAlchemy"
    },
    {
      "src": "assets/icons/sqlite-svgrepo-com.svg",
      "text": "SQLite"
    },
    {
      "src": "assets/icons/bash-icon-svgrepo-com.svg",
      "text": "Bash"
    },
    {
      "src": "assets/icons/git-svgrepo-com.svg",
      "text": "Git"
    },
    {
      "src": "assets/icons/github.svg",
      "text": "GitHub"
    },
    {
      "src": "assets/icons/docker-svgrepo-com.svg",
      "text": "Docker"
    }
  ],
  [
    {
      "src": "assets/icons/amazonec2.svg",
      "text": "Amazon EC2"
    },
    {
      "src": "assets/icons/amazons3.svg",
      "text": "Amazon S3"
    }
  ]
]